.gitignore
.travis.yml
AUTHORS.rst
CONTRIBUTING.rst
HISTORY.rst
LICENSE
MANIFEST.in
README.md
setup.py
test_yaconfigobject.py
tox.ini
yaconfigobject.py
doc/Makefile
doc/authors.rst
doc/conf.py
doc/contributing.rst
doc/history.rst
doc/index.rst
doc/installation.rst
doc/usage.rst
doc/yaconfigobject.rst
yaconfigobject.egg-info/PKG-INFO
yaconfigobject.egg-info/SOURCES.txt
yaconfigobject.egg-info/dependency_links.txt
yaconfigobject.egg-info/requires.txt
yaconfigobject.egg-info/top_level.txt