Metadata-Version: 2.1
Name: yaconfigobject
Version: 1.2.3
Summary: A library representing YAML config files as object.
Home-page: https://github.com/MeteoSwiss/yaconfigobject
Author: Philipp Falke
Author-email: philipp.falke@meteoswiss.ch
License: BSD-3-Clause license
Keywords: yaconfigobject
Platform: UNKNOWN
Classifier: Development Status :: 4 - Beta
Classifier: Intended Audience :: Developers
Classifier: License :: OSI Approved :: BSD License
Classifier: Natural Language :: English
Classifier: Programming Language :: Python :: 3.6
Classifier: Programming Language :: Python :: 3.7
Classifier: Programming Language :: Python :: 3.8
Provides-Extra: test
